[{"__EMPTY":"Semester wise breakdown - BSAI"},{"__EMPTY":"Semester 1"},{"__EMPTY":"SNo","__EMPTY_1":"Course \n Code","__EMPTY_2":"Subject","__EMPTY_3":"CHs \n Teaching","__EMPTY_4":"CHs \n Labs","__EMPTY_5":"Pre-Req","__EMPTY_6":"Dept.","__EMPTY_7":"Semester"},{"__EMPTY":1,"__EMPTY_1":"CS-108","__EMPTY_2":"Application of Info. & Comm. Technologies","__EMPTY_3":2,"__EMPTY_4":1,"__EMPTY_6":"FoC","__EMPTY_7":"1st"},{"__EMPTY":2,"__EMPTY_1":"CS-110","__EMPTY_2":"Fundamentals of Computer Programming","__EMPTY_3":3,"__EMPTY_4":1,"__EMPTY_6":"FoC"},{"__EMPTY":"3.a","__EMPTY_1":"MATH-161","__EMPTY_2":"Discrete Mathematics","__EMPTY_3":3,"__EMPTY_4":0,"__EMPTY_6":"H&S"},{"__EMPTY":"4.a","__EMPTY_1":"MATH-101","__EMPTY_2":"Calculus & Analytical Geometry","__EMPTY_3":3,"__EMPTY_4":0,"__EMPTY_6":"H&S"},{"__EMPTY":5,"__EMPTY_1":"HU-114","__EMPTY_2":"Functional English","__EMPTY_3":3,"__EMPTY_4":0,"__EMPTY_6":"H&S"},{"__EMPTY":6,"__EMPTY_1":"HU-131","__EMPTY_2":"Understanding of Holy Quran - I / Fehm-e-Quran - I","__EMPTY_3":0,"__EMPTY_4":1,"__EMPTY_6":"H&S"},{"__EMPTY":"For Pre- medical Students only (Semester-1)"},{"__EMPTY":"3.b","__EMPTY_1":"MATH-162","__EMPTY_2":"Pre-Mathematics-1 (in place of MATH-161)","__EMPTY_3":3,"__EMPTY_4":0,"__EMPTY_6":"H&S"},{"__EMPTY":"4.b","__EMPTY_1":"MATH-163","__EMPTY_2":"Pre-Mathematics-2 (in place of MATH-101)","__EMPTY_3":3,"__EMPTY_4":0,"__EMPTY_6":"H&S"},{"__EMPTY":"Total CHs ","__EMPTY_3":14,"__EMPTY_4":3,"__EMPTY_7":17},{"__EMPTY":"Semester 2"},{"__EMPTY":"SNo","__EMPTY_1":"Course \n Code","__EMPTY_2":"Subject","__EMPTY_3":"CHs \n Teaching","__EMPTY_4":"CHs \n Labs","__EMPTY_5":"Pre-Req","__EMPTY_6":"Dept.","__EMPTY_7":"Semester"},{"__EMPTY":1,"__EMPTY_1":"CS-212","__EMPTY_2":"Object Oriented Programming (OOP)","__EMPTY_3":3,"__EMPTY_4":1,"__EMPTY_5":"CS-110, FOCP","__EMPTY_6":"FoC","__EMPTY_7":"2nd "},{"__EMPTY":2,"__EMPTY_1":"CS-220","__EMPTY_2":"Database Systems","__EMPTY_3":3,"__EMPTY_4":1,"__EMPTY_6":"FoC"},{"__EMPTY":3,"__EMPTY_1":"EE-223","__EMPTY_2":"Digital Logic Design (DLD)","__EMPTY_3":2,"__EMPTY_4":1,"__EMPTY_6":"EE"},{"__EMPTY":"4.a","__EMPTY_1":"MATH-234","__EMPTY_2":"Multivariable Calculus","__EMPTY_3":3,"__EMPTY_4":0,"__EMPTY_5":"Math-101, Calculus & Analytical Geometry","__EMPTY_6":"H&S"},{"__EMPTY":"5.a","__EMPTY_1":"MATH-222","__EMPTY_2":"Linear Algebra","__EMPTY_3":3,"__EMPTY_4":0,"__EMPTY_5":"Math-101, Calculus & Analytical Geometry","__EMPTY_6":"H&S"},{"__EMPTY":6,"__EMPTY_1":"HU-132","__EMPTY_2":"Understanding of Holy Quran - II / Fehm-e-Quran - II","__EMPTY_3":0,"__EMPTY_4":1,"__EMPTY_5":"HU-XXX-I","__EMPTY_6":"H&S"},{"__EMPTY":"For Pre- medical Students only (Semester-2)"},{"__EMPTY":"4.b","__EMPTY_1":"MATH-161","__EMPTY_2":"Discrete Mathematics (in place of MATH-234)","__EMPTY_3":3,"__EMPTY_4":0,"__EMPTY_6":"H&S"},{"__EMPTY":"5.b","__EMPTY_1":"MATH-101","__EMPTY_2":"Calculus & Analytical Geometry (in place of MATH-222","__EMPTY_3":3,"__EMPTY_4":0,"__EMPTY_6":"H&S"},{"__EMPTY":"Total CHs ","__EMPTY_3":14,"__EMPTY_4":4,"__EMPTY_7":18},{"__EMPTY":"Total CHs (with Pre-Medical)","__EMPTY_3":14,"__EMPTY_4":4,"__EMPTY_7":18},{"__EMPTY":"Summer Semester (For pre medical student only)"},{"__EMPTY":"SNo","__EMPTY_1":"Course \n Code","__EMPTY_2":"Subject","__EMPTY_3":"CHs \n Teaching","__EMPTY_4":"CHs \n Labs","__EMPTY_5":"Pre-Req","__EMPTY_6":"Dept.","__EMPTY_7":"Semester"},{"__EMPTY_7":"2nd "},{"__EMPTY":"For Pre- medical Students only"},{"__EMPTY":1,"__EMPTY_1":"MATH-234","__EMPTY_2":"Multivariable Calculus","__EMPTY_3":3,"__EMPTY_4":0,"__EMPTY_5":"Math-101, Calculus & Analytical Geometry","__EMPTY_6":"H&S"},{"__EMPTY":2,"__EMPTY_1":"MATH-222","__EMPTY_2":"Linear Algebra","__EMPTY_3":3,"__EMPTY_4":0,"__EMPTY_5":"Math-101, Calculus & Analytical Geometry","__EMPTY_6":"H&S"},{"__EMPTY":"Total CHs ","__EMPTY_3":14,"__EMPTY_4":4,"__EMPTY_7":18},{"__EMPTY":"Semester 3"},{"__EMPTY":"SNo","__EMPTY_1":"Course \n Code","__EMPTY_2":"Subject","__EMPTY_3":"CHs \n Teaching","__EMPTY_4":"CHs \n Labs","__EMPTY_5":"Pre-Req","__EMPTY_6":"Dept.","__EMPTY_7":"Semester"},{"__EMPTY":1,"__EMPTY_1":"CS-250","__EMPTY_2":"Data Structures & Algorithms (DSA)","__EMPTY_3":3,"__EMPTY_4":1,"__EMPTY_5":"CS-110, FoCP","__EMPTY_6":"FoC","__EMPTY_7":"3rd"},{"__EMPTY":2,"__EMPTY_1":"CS-353","__EMPTY_2":"Information Security","__EMPTY_3":2,"__EMPTY_4":1,"__EMPTY_6":"FoC"},{"__EMPTY":3,"__EMPTY_1":"CS-272","__EMPTY_2":"Artificial Intelligence","__EMPTY_3":2,"__EMPTY_4":1,"__EMPTY_6":"FoC"},{"__EMPTY":4,"__EMPTY_1":"EE-347","__EMPTY_2":"Computer Networks","__EMPTY_3":2,"__EMPTY_4":1,"__EMPTY_6":"FoC"},{"__EMPTY":5,"__EMPTY_1":"MATH-361","__EMPTY_2":"Probability & Statistics","__EMPTY_3":3,"__EMPTY_4":0,"__EMPTY_6":"H&S"},{"__EMPTY":6,"__EMPTY_1":"HU-101","__EMPTY_2":"Islamic Studies OR Religious Education / Ethics for Non-Muslim students","__EMPTY_3":2,"__EMPTY_4":0,"__EMPTY_6":"H&S"},{"__EMPTY":"Total CHs ","__EMPTY_3":14,"__EMPTY_4":4,"__EMPTY_7":18},{"__EMPTY":"Semester 4"},{"__EMPTY":"SNo","__EMPTY_1":"Course \n Code","__EMPTY_2":"Subject","__EMPTY_3":"CHs \n Teaching","__EMPTY_4":"CHs \n Labs","__EMPTY_5":"Pre-Req","__EMPTY_6":"Dept.","__EMPTY_7":"Semester"},{"__EMPTY":1,"__EMPTY_1":"CS-234","__EMPTY_2":"Computer Organization & Assembly Language","__EMPTY_3":2,"__EMPTY_4":1,"__EMPTY_5":"EE-223, DLD","__EMPTY_6":"FoC","__EMPTY_7":"4th"},{"__EMPTY":2,"__EMPTY_1":"CS-2XX","__EMPTY_2":"Programming for AI (Domain Core 1)","__EMPTY_3":2,"__EMPTY_4":1,"__EMPTY_6":"FoC"},{"__EMPTY":3,"__EMPTY_1":"CS-245","__EMPTY_2":"Machine Learning (Domain Core 2)","__EMPTY_3":2,"__EMPTY_4":1,"__EMPTY_6":"FoC"},{"__EMPTY":4,"__EMPTY_1":"Phy-102","__EMPTY_2":"Applied Physics (Any Course from General Education Requirements)","__EMPTY_3":2,"__EMPTY_4":1,"__EMPTY_6":"H&S"},{"__EMPTY":5,"__EMPTY_1":"ENGL-104","__EMPTY_2":"Expository Writing","__EMPTY_3":3,"__EMPTY_4":0,"__EMPTY_5":"HU-114, Functional English","__EMPTY_6":"H&S"},{"__EMPTY":6,"__EMPTY_1":"CS-3XX","__EMPTY_2":"AI Elective-1","__EMPTY_3":2,"__EMPTY_4":1,"__EMPTY_6":"FoC"},{"__EMPTY":"Total CHs ","__EMPTY_3":13,"__EMPTY_4":5,"__EMPTY_7":18},{"__EMPTY":"Semester 5"},{"__EMPTY":"SNo","__EMPTY_1":"Course \n Code","__EMPTY_2":"Subject","__EMPTY_3":"CHs \n Teaching","__EMPTY_4":"CHs \n Labs","__EMPTY_5":"Pre-Req","__EMPTY_6":"Dept.","__EMPTY_7":"Semester"},{"__EMPTY":1,"__EMPTY_1":"CS-333","__EMPTY_2":"Operating System","__EMPTY_3":2,"__EMPTY_4":1,"__EMPTY_6":"FoC","__EMPTY_7":"5th"},{"__EMPTY":2,"__EMPTY_1":"CS-3XX","__EMPTY_2":"Artificial Neural Networks & Deep Learning (Domain Core 3)","__EMPTY_3":2,"__EMPTY_4":1,"__EMPTY_6":"FoC"},{"__EMPTY":3,"__EMPTY_1":"CS-3XX","__EMPTY_2":"Knowledge Representation & Reasoning (Domain Core 4)","__EMPTY_3":2,"__EMPTY_4":1,"__EMPTY_6":"FoC"},{"__EMPTY":4,"__EMPTY_1":"MGT-164","__EMPTY_2":"Introduction to Management","__EMPTY_3":2,"__EMPTY_4":0,"__EMPTY_6":"H&S"},{"__EMPTY":5,"__EMPTY_1":"CS-3XX","__EMPTY_2":"AI Elective-2","__EMPTY_3":2,"__EMPTY_4":1,"__EMPTY_6":"FoC"},{"__EMPTY":6,"__EMPTY_1":"CS-3XX","__EMPTY_2":"AI Elective-3","__EMPTY_3":2,"__EMPTY_4":1,"__EMPTY_6":"FoC"},{"__EMPTY":"Total CHs ","__EMPTY_3":12,"__EMPTY_4":5,"__EMPTY_7":17},{"__EMPTY":"Semester 6"},{"__EMPTY":"SNo","__EMPTY_1":"Course \n Code","__EMPTY_2":"Subject","__EMPTY_3":"CHs \n Teaching","__EMPTY_4":"CHs \n Labs","__EMPTY_5":"Pre-Req","__EMPTY_6":"Dept.","__EMPTY_7":"Semester"},{"__EMPTY":1,"__EMPTY_1":"CS-347","__EMPTY_2":"Parallel & Distributed Computing (Domain Core 5)","__EMPTY_3":2,"__EMPTY_4":1,"__EMPTY_6":"FoC","__EMPTY_7":"6th"},{"__EMPTY":2,"__EMPTY_1":"CS-474","__EMPTY_2":"Computer Vision  (Domain Core 6)","__EMPTY_3":2,"__EMPTY_4":1,"__EMPTY_6":"FoC"},{"__EMPTY":3,"__EMPTY_1":"HU-127","__EMPTY_2":"Ideology and Constitution of Pakistan ","__EMPTY_3":2,"__EMPTY_4":0,"__EMPTY_6":"H&S"},{"__EMPTY":4,"__EMPTY_1":"CS-3XX","__EMPTY_2":"AI Elective-4","__EMPTY_3":2,"__EMPTY_4":1,"__EMPTY_6":"FoC"},{"__EMPTY":5,"__EMPTY_1":"CS-3XX","__EMPTY_2":"AI Elective-5","__EMPTY_3":2,"__EMPTY_4":1,"__EMPTY_6":"FoC"},{"__EMPTY":6,"__EMPTY_1":"CS-3XX","__EMPTY_2":"AI Elective-6","__EMPTY_3":2,"__EMPTY_4":1,"__EMPTY_6":"FoC"},{"__EMPTY":"Total CHs ","__EMPTY_3":12,"__EMPTY_4":5,"__EMPTY_7":17},{"__EMPTY":"Semester 7"},{"__EMPTY":"SNo","__EMPTY_1":"Course \n Code","__EMPTY_2":"Subject","__EMPTY_3":"CHs \n Teaching","__EMPTY_4":"CHs \n Labs","__EMPTY_5":"Pre-Req","__EMPTY_6":"Dept.","__EMPTY_7":"Semester"},{"__EMPTY":1,"__EMPTY_1":"AI-498","__EMPTY_2":"Final Year Project - I","__EMPTY_3":0,"__EMPTY_4":2,"__EMPTY_6":"FoC","__EMPTY_7":"7th"},{"__EMPTY":2,"__EMPTY_1":"CS-251","__EMPTY_2":"Design & Analysis of Algorithms","__EMPTY_3":3,"__EMPTY_4":0,"__EMPTY_5":"CS-250, DSA","__EMPTY_6":"FoC"},{"__EMPTY":3,"__EMPTY_1":"HU-212","__EMPTY_2":"Technical & Business Writing","__EMPTY_3":3,"__EMPTY_4":0,"__EMPTY_5":"HU-114, Functional English","__EMPTY_6":"H&S"},{"__EMPTY":4,"__EMPTY_1":"MGT-271","__EMPTY_2":"Entrepreneurship","__EMPTY_3":2,"__EMPTY_4":0,"__EMPTY_6":"H&S"},{"__EMPTY":5,"__EMPTY_1":"CS-4XX","__EMPTY_2":"AI Elective-7","__EMPTY_3":2,"__EMPTY_4":1,"__EMPTY_6":"FoC"},{"__EMPTY":6,"__EMPTY_1":"HU 107","__EMPTY_2":"Pakistan Studies","__EMPTY_3":2,"__EMPTY_4":0,"__EMPTY_6":"H&S"},{"__EMPTY":"Total CHs ","__EMPTY_3":12,"__EMPTY_4":3,"__EMPTY_7":15},{"__EMPTY":"Semester 8"},{"__EMPTY":"SNo","__EMPTY_1":"Course \n Code","__EMPTY_2":"Subject","__EMPTY_3":"CHs \n Teaching","__EMPTY_4":"CHs \n Labs","__EMPTY_5":"Pre-Req","__EMPTY_6":"Dept.","__EMPTY_7":"Semester"},{"__EMPTY":1,"__EMPTY_1":"CS-250","__EMPTY_2":"Final Year Project - II","__EMPTY_3":0,"__EMPTY_4":4,"__EMPTY_5":"DS-498, Final Year Project - I ","__EMPTY_6":"FoC","__EMPTY_7":"8th"},{"__EMPTY":2,"__EMPTY_1":"SE-200","__EMPTY_2":"Software Engineering*","__EMPTY_3":3,"__EMPTY_4":0,"__EMPTY_6":"FoC"},{"__EMPTY":3,"__EMPTY_1":"CS-2XX","__EMPTY_2":"Civic and Community Engagement","__EMPTY_3":1,"__EMPTY_4":1,"__EMPTY_6":"FoC"},{"__EMPTY":4,"__EMPTY_1":"HU-223","__EMPTY_2":"Professional Ethics (Any Course from General Education Requirements)","__EMPTY_3":3,"__EMPTY_4":0,"__EMPTY_6":"H&S"},{"__EMPTY":5,"__EMPTY_1":"HU-102","__EMPTY_2":"Psychology (Any Course from Elective Supporting)","__EMPTY_3":3,"__EMPTY_4":0,"__EMPTY_6":"H&S"},{"__EMPTY":"Total CHs ","__EMPTY_3":10,"__EMPTY_4":5,"__EMPTY_7":15}]